Workbook

Sheet Home
A1: PROJECT
A9: BY
A14: Suleman Arshad 220746 Aimen Shabir 220804 Duaa Faisal 220802 Ubaid ur Rehman 220810 Iraj Shaukat 220760

Sheet Financial model
D9: Financial model
A12: Sales growth | B12: 0.1 | D12: Year | E12: 2024 | F12: 2025 | G12: 2026 | H12: 2027 | I12: 2028 | J12: 2029 | K12: 2030 | L12: 2031 | M12: 2032 | N12: 2033 | O12: 2034
A13: Current assets/Sales | B13: 0.15 | E13: $ ,000 | F13: $ ,000 | G13: $ ,000 | H13: $ ,000 | I13: $ ,000 | J13: $ ,000 | K13: $ ,000 | L13: $ ,000 | M13: $ ,000 | N13: $ ,000 | O13: $ ,000
A14: Current liabilities/Sales | B14: 0.08 | D14: Income Statement
A15: Net fixed assets/Sales | B15: 0.4 | D15: Sales | E15: 427946 | F15: =E15*(1+$B$12) -> 470740.6 | G15: =F15*(1+$B$12) -> 517814.66 | H15: =G15*(1+$B$12) -> 569596.13 | I15: =H15*(1+$B$12) -> 626555.74 | J15: =I15*(1+$B$12) -> 689211.31 | K15: =J15*(1+$B$12) -> 758132.44 | L15: =K15*(1+$B$12) -> 833945.69 | M15: =L15*(1+$B$12) -> 917340.26 | ... O15: =N15*(1+$B$12) -> 1109981.7
A16: Capex/Sales | B16: 0.12 | D16: Costs of goods sold | E16: -405841 | F16: =-F15*$B$17 -> -235370.3 | G16: =-G15*$B$17 -> -258907.33 | H16: =-H15*$B$17 -> -284798.06 | I16: =-I15*$B$17 -> -313277.87 | J16: =-J15*$B$17 -> -344605.66 | K16: =-K15*$B$17 -> -379066.22 | L16: =-L15*$B$17 -> -416972.84 | M16: =-M15*$B$17 -> -458670.13 | ... O16: =-O15*$B$17 -> -554990.86
A17: Costs of goods sold/Sales | B17: 0.5 | D17: Operating expenses | F17: =$B$21*-F15 -> -94148.12 | G17: =$B$21*-G15 -> -103562.93 | H17: =$B$21*-H15 -> -113919.23 | I17: =$B$21*-I15 -> -125311.15 | J17: =$B$21*-J15 -> -137842.26 | K17: =$B$21*-K15 -> -151626.49 | L17: =$B$21*-L15 -> -166789.14 | M17: =$B$21*-M15 -> -183468.05 | ... O17: =$B$21*-O15 -> -221996.34
A18: Depreciation rate | B18: 0.1 | D18: Interest payments on debt | E18: -6371 | F18: =-$B$20*(E37+F37)/2 -> -2696.0325 | G18: =-$B$20*(F37+G37)/2 -> -6021.8664 | H18: =-$B$20*(G37+H37)/2 -> -9216.6967 | I18: =-$B$20*(H37+I37)/2 -> -12737.985 | J18: =-$B$20*(I37+J37)/2 -> -16612.226 | K18: =-$B$20*(J37+K37)/2 -> -20867.738 | L18: =-$B$20*(K37+L37)/2 -> -25534.754 | M18: =-$B$20*(L37+M37)/2 -> -30645.512 | ... O18: =-$B$20*(N37+O37)/2 -> -42337.756
A19: Asset life for Depreciation | B19: 10 years | D19: Interest earned on cash and m. securities | E19: 1244 | F19: =$B$22*(E28+F28)/2 -> -3727.0982 | G19: =$B$22*(F28+G28)/2 -> -6541.1061 | H19: =$B$22*(G28+H28)/2 -> -2009.9294 | I19: =$B$22*(H28+I28)/2 -> 2988.3149 | J19: =$B$22*(I28+J28)/2 -> 8488.0313 | K19: =$B$22*(J28+K28)/2 -> 14525.414 | L19: =$B$22*(K28+L28)/2 -> 21138.44 | M19: =$B$22*(L28+M28)/2 -> 28366.849 | ... O19: =$B$22*(N28+O28)/2 -> 44837.259
A20: Interest rate on debt | B20: 0.12 | D20: Depreciation | E20: -3255 | F20: =-$B$18*(E31+F31)/2 -> -12757.381 | G20: =-$B$18*(F31+G31)/2 -> -23923.73 | H20: =-$B$18*(G31+H31)/2 -> -28523.186 | I20: =-$B$18*(H31+I31)/2 -> -33814.913 | J20: =-$B$18*(I31+J31)/2 -> -39892.592 | K20: =-$B$18*(J31+K31)/2 -> -46861.848 | L20: =-$B$18*(K31+L31)/2 -> -54841.713 | M20: =-$B$18*(L31+M31)/2 -> -63966.269 | ... O20: =-$B$18*(N31+O31)/2 -> -86272.243
A21: Operating expenses/sales | B21: 0.2 | D21: Profit before tax | E21: 7146 | F21: =SUM(F15:F20) -> 122041.67 | G21: =SUM(G15:G20) -> 118857.7 | H21: =SUM(H15:H20) -> 131129.03 | I21: =SUM(I15:I20) -> 144402.14 | J21: =SUM(J15:J20) -> 158746.61 | K21: =SUM(K15:K20) -> 174235.56 | L21: =SUM(L15:L20) -> 190945.68 | M21: =SUM(M15:M20) -> 208957.15 | ... O21: =SUM(O15:O20) -> 249221.77
A22: Interest rate on cash and marketable securities | B22: 0.08 | D22: Taxes | E22: -3849 | F22: =-F21*$B$23 -> -35392.084 | G22: =-G21*$B$23 -> -34468.732 | H22: =-H21*$B$23 -> -38027.417 | I22: =-I21*$B$23 -> -41876.62 | J22: =-J21*$B$23 -> -46036.516 | K22: =-K21*$B$23 -> -50528.313 | L22: =-L21*$B$23 -> -55374.247 | M22: =-M21*$B$23 -> -60597.572 | ... O22: =-O21*$B$23 -> -72274.314
A23: Tax rate | B23: 0.29 | D23: Profit after tax | E23: 3297 | F23: =F21+F22 -> 86649.584 | G23: =G21+G22 -> 84388.964 | H23: =H21+H22 -> 93101.608 | I23: =I21+I22 -> 102525.52 | J23: =J21+J22 -> 112710.09 | K23: =K21+K22 -> 123707.25 | L23: =L21+L22 -> 135571.43 | M23: =M21+M22 -> 148359.57 | ... O23: =O21+O22 -> 176947.46
A24: Dividend payout ratio | B24: 0.4 | D24: Dividends | E24: -1071 | F24: =-F23*$B$24 -> -34659.834 | G24: =-G23*$B$24 -> -33755.586 | H24: =-H23*$B$24 -> -37240.643 | I24: =-I23*$B$24 -> -41010.207 | J24: =-J23*$B$24 -> -45084.037 | K24: =-K23*$B$24 -> -49482.899 | L24: =-L23*$B$24 -> -54228.573 | M24: =-M23*$B$24 -> -59343.829 | ... O24: =-O23*$B$24 -> -70778.984
A25: Target Debt to Equity Ratio | B25: 0.5 | D25: Retained earnings | E25: 2226 | F25: =F23+F24 -> 51989.751 | G25: =G23+G24 -> 50633.378 | H25: =H23+H24 -> 55860.965 | I25: =I23+I24 -> 61515.311 | J25: =J23+J24 -> 67626.055 | K25: =K23+K24 -> 74224.349 | L25: =L23+L24 -> 81342.859 | M25: =M23+M24 -> 89015.744 | ... O25: =O23+O24 -> 106168.48
D27: Balance sheet
D28: Cash and marketable securities | E28: 15499 | F28: =F40-F33-F29 -> -108676.46 | G28: =G40-G33-G29 -> -54851.197 | H28: =H40-H33-H29 -> 4602.9617 | I28: =I40-I33-I29 -> 70104.91 | J28: =J40-J33-J29 -> 142095.87 | K28: =K40-K33-K29 -> 221039.46 | L28: =L40-L33-L29 -> 307421.53 | M28: =M40-M33-M29 -> 401749.7 | ... O28: =O40-O33-O29 -> 616378.85
D29: Current assets | E29: 93965 | F29: =F15*$B$13 -> 70611.09 | G29: =G15*$B$13 -> 77672.199 | H29: =H15*$B$13 -> 85439.419 | I29: =I15*$B$13 -> 93983.361 | J29: =J15*$B$13 -> 103381.7 | K29: =K15*$B$13 -> 113719.87 | L29: =L15*$B$13 -> 125091.85 | M29: =M15*$B$13 -> 137601.04 | ... O29: =O15*$B$13 -> 166497.26
D30: Fixed assets
D31: At cost | E31: 37287 | F31: =F33-F32 -> 217860.62 | G31: =G33-G32 -> 260613.97 | H31: =H33-H32 -> 309849.75 | I31: =I33-I32 -> 366448.51 | J31: =J33-J32 -> 431403.33 | K31: =K33-K32 -> 505833.63 | L31: =L33-L32 -> 591000.64 | M31: =M33-M32 -> 688324.73 | ... O31: =O33-O32 -> 926040.04
D32: Depreciation | E32: -16807 | F32: =E32+F20 -> -29564.381 | G32: =F32+G20 -> -53488.111 | H32: =G32+H20 -> -82011.297 | I32: =H32+I20 -> -115826.21 | J32: =I32+J20 -> -155718.8 | K32: =J32+K20 -> -202580.65 | L32: =K32+L20 -> -257422.36 | M32: =L32+M20 -> -321388.63 | ... O32: =N32+O20 -> -482047.35
D33: Net fixed assets | E33: 20480 | F33: =$B$15*F15 -> 188296.24 | G33: =$B$15*G15 -> 207125.86 | H33: =$B$15*H15 -> 227838.45 | I33: =$B$15*I15 -> 250622.3 | J33: =$B$15*J15 -> 275684.52 | K33: =$B$15*K15 -> 303252.98 | L33: =$B$15*L15 -> 333578.28 | M33: =$B$15*M15 -> 366936.1 | ... O33: =$B$15*O15 -> 443992.68
D34: Total assets | E34: 114445 | F34: =F33+F29+F28 -> 150230.87 | G34: =G33+G29+G28 -> 229946.87 | H34: =H33+H29+H28 -> 317880.83 | I34: =I33+I29+I28 -> 414710.57 | J34: =J33+J29+J28 -> 521162.09 | K34: =K33+K29+K28 -> 638012.31 | L34: =L33+L29+L28 -> 766091.66 | M34: =M33+M29+M28 -> 906286.84 | ... O34: =O33+O29+O28 -> 1226868.8
D36: Current liabilities | E36: 83977 | F36: =$B$14*F15 -> 37659.248 | G36: =$B$14*G15 -> 41425.173 | H36: =$B$14*H15 -> 45567.69 | I36: =$B$14*I15 -> 50124.459 | J36: =$B$14*J15 -> 55136.905 | K36: =$B$14*K15 -> 60650.595 | L36: =$B$14*L15 -> 66715.655 | M36: =$B$14*M15 -> 73387.221 | ... O36: =$B$14*O15 -> 88798.537
D37: Debt | E37: 7410 | F37: =$B$25*(F38+F39) -> 37523.875 | G37: =$B$25*(G38+G39) -> 62840.565 | H37: =$B$25*(H38+H39) -> 90771.047 | I37: =$B$25*(I38+I39) -> 121528.7 | J37: =$B$25*(J38+J39) -> 155341.73 | K37: =$B$25*(K38+K39) -> 192453.9 | L37: =$B$25*(L38+L39) -> 233125.33 | M37: =$B$25*(M38+M39) -> 277633.21 | ... O37: =$B$25*(O38+O39) -> 379356.75
D38: Stock | E38: 13486 | F38: 13486 | G38: 13486 | H38: 13486 | I38: 13486 | J38: 13486 | K38: 13486 | L38: 13486 | M38: 13486 | N38: 13486 | O38: 13486
D39: Accumulated retained earnings | E39: 9572 | F39: =E39+F25 -> 61561.751 | G39: =F39+G25 -> 112195.13 | H39: =G39+H25 -> 168056.09 | I39: =H39+I25 -> 229571.41 | J39: =I39+J25 -> 297197.46 | K39: =J39+K25 -> 371421.81 | L39: =K39+L25 -> 452764.67 | M39: =L39+M25 -> 541780.41 | ... O39: =N39+O25 -> 745227.5
D40: Total liabilities and equity | E40: 114445 | F40: =SUM(F36:F39) -> 150230.87 | G40: =SUM(G36:G39) -> 229946.87 | H40: =SUM(H36:H39) -> 317880.83 | I40: =SUM(I36:I39) -> 414710.57 | J40: =SUM(J36:J39) -> 521162.09 | K40: =SUM(K36:K39) -> 638012.31 | L40: =SUM(L36:L39) -> 766091.66 | M40: =SUM(M36:M39) -> 906286.84 | ... O40: =SUM(O36:O39) -> 1226868.8

Sheet Free Cash Flows
B9: Free CASH FLOW
B12: Year | C12: 2024 | D12: 2025 | E12: 2026 | F12: 2027 | G12: 2028 | H12: 2029 | I12: 2030 | J12: 2031 | K12: 2032 | L12: 2033 | M12: 2034
B13: Profit After Tax | D13: ='Financial model'!F23 -> 86649.584 | E13: ='Financial model'!G23 -> 84388.964 | F13: ='Financial model'!H23 -> 93101.608 | G13: ='Financial model'!I23 -> 102525.52 | H13: ='Financial model'!J23 -> 112710.09 | I13: ='Financial model'!K23 -> 123707.25 | J13: ='Financial model'!L23 -> 135571.43 | K13: ='Financial model'!M23 -> 148359.57 | ... M13: ='Financial model'!O23 -> 176947.46
B14: Add: Depreciation | D14: =-'Financial model'!F20 -> 12757.381 | E14: =-'Financial model'!G20 -> 23923.73 | F14: =-'Financial model'!H20 -> 28523.186 | G14: =-'Financial model'!I20 -> 33814.913 | H14: =-'Financial model'!J20 -> 39892.592 | I14: =-'Financial model'!K20 -> 46861.848 | J14: =-'Financial model'!L20 -> 54841.713 | K14: =-'Financial model'!M20 -> 63966.269 | ... M14: =-'Financial model'!O20 -> 86272.243
B15: Subtract: Increase in Current assets | D15: =-('Financial model'!F29-'Financial model'!E29) -> 23353.91 | E15: =-('Financial model'!G29-'Financial model'!F29) -> -7061.109 | F15: =-('Financial model'!H29-'Financial model'!G29) -> -7767.2199 | G15: =-('Financial model'!I29-'Financial model'!H29) -> -8543.9419 | H15: =-('Financial model'!J29-'Financial model'!I29) -> -9398.3361 | I15: =-('Financial model'!K29-'Financial model'!J29) -> -10338.17 | J15: =-('Financial model'!L29-'Financial model'!K29) -> -11371.987 | K15: =-('Financial model'!M29-'Financial model'!L29) -> -12509.185 | ... M15: =-('Financial model'!O29-'Financial model'!N29) -> -15136.114
B16: Add: Increase in Current Liabilities | D16: ='Financial model'!F36-'Financial model'!E36 -> -46317.752 | E16: ='Financial model'!G36-'Financial model'!F36 -> 3765.9248 | F16: ='Financial model'!H36-'Financial model'!G36 -> 4142.5173 | G16: ='Financial model'!I36-'Financial model'!H36 -> 4556.769 | H16: ='Financial model'!J36-'Financial model'!I36 -> 5012.4459 | I16: ='Financial model'!K36-'Financial model'!J36 -> 5513.6905 | J16: ='Financial model'!L36-'Financial model'!K36 -> 6065.0595 | K16: ='Financial model'!M36-'Financial model'!L36 -> 6671.5655 | ... M16: ='Financial model'!O36-'Financial model'!N36 -> 8072.5943
B17: Subtract: Increase in fixed assets at cost | D17: =-('Financial model'!F31-'Financial model'!E31) -> -180573.62 | E17: =-('Financial model'!G31-'Financial model'!F31) -> -42753.354 | F17: =-('Financial model'!H31-'Financial model'!G31) -> -49235.773 | G17: =-('Financial model'!I31-'Financial model'!H31) -> -56598.758 | H17: =-('Financial model'!J31-'Financial model'!I31) -> -64954.821 | I17: =-('Financial model'!K31-'Financial model'!J31) -> -74430.3 | J17: =-('Financial model'!L31-'Financial model'!K31) -> -85167.011 | K17: =-('Financial model'!M31-'Financial model'!L31) -> -97324.096 | ... M17: =-('Financial model'!O31-'Financial model'!N31) -> -126635.21
B18: Add: After-tax interest on debt | D18: =-('Financial model'!F18*(1-'Financial model'!$B$23)) -> 1914.1831 | E18: =-('Financial model'!G18*(1-'Financial model'!$B$23)) -> 4275.5251 | F18: =-('Financial model'!H18*(1-'Financial model'!$B$23)) -> 6543.8546 | G18: =-('Financial model'!I18*(1-'Financial model'!$B$23)) -> 9043.9693 | H18: =-('Financial model'!J18*(1-'Financial model'!$B$23)) -> 11794.68 | I18: =-('Financial model'!K18*(1-'Financial model'!$B$23)) -> 14816.094 | J18: =-('Financial model'!L18*(1-'Financial model'!$B$23)) -> 18129.676 | K18: =-('Financial model'!M18*(1-'Financial model'!$B$23)) -> 21758.314 | ... M18: =-('Financial model'!O18*(1-'Financial model'!$B$23)) -> 30059.807
B19: Subtract: After-tax interest on Cash and Marketable securities | D19: =-('Financial model'!F19*(1-'Financial model'!$B$23)) -> 2646.2398 | E19: =-('Financial model'!G19*(1-'Financial model'!$B$23)) -> 4644.1853 | F19: =-('Financial model'!H19*(1-'Financial model'!$B$23)) -> 1427.0499 | G19: =-('Financial model'!I19*(1-'Financial model'!$B$23)) -> -2121.7036 | H19: =-('Financial model'!J19*(1-'Financial model'!$B$23)) -> -6026.5023 | I19: =-('Financial model'!K19*(1-'Financial model'!$B$23)) -> -10313.044 | J19: =-('Financial model'!L19*(1-'Financial model'!$B$23)) -> -15008.292 | K19: =-('Financial model'!M19*(1-'Financial model'!$B$23)) -> -20140.463 | ... M19: =-('Financial model'!O19*(1-'Financial model'!$B$23)) -> -31834.454
B20: FREE CASH FLOW | D20: =SUM(D13:D19) -> -99570.075 | E20: =SUM(E13:E19) -> 71183.866 | F20: =SUM(F13:F19) -> 76735.224 | G20: =SUM(G13:G19) -> 82676.766 | H20: =SUM(H13:H19) -> 89030.15 | I20: =SUM(I13:I19) -> 95817.367 | J20: =SUM(J13:J19) -> 103060.59 | K20: =SUM(K13:K19) -> 110781.98 | ... M20: =SUM(M13:M19) -> 127746.32

Sheet Statement of Cashflows
B9: CONSOLIDATED STATEMENT OF CASH FLOWS: RECONCILING THE CASH BALANCES
B12: Cash flow from operating activities | C12: 2025 | D12: 2026 | E12: 2027 | F12: 2028 | G12: 2029 | H12: 2030 | I12: 2031 | J12: 2032 | K12: 2033 | L12: 2034
B13: Profit after tax | C13: ='Financial model'!F23 -> 86649.584 | D13: ='Financial model'!G23 -> 84388.964 | E13: ='Financial model'!H23 -> 93101.608 | F13: ='Financial model'!I23 -> 102525.52 | G13: ='Financial model'!J23 -> 112710.09 | H13: ='Financial model'!K23 -> 123707.25 | I13: ='Financial model'!L23 -> 135571.43 | J13: ='Financial model'!M23 -> 148359.57 | ... L13: ='Financial model'!O23 -> 176947.46
B14: Add back depreciation | C14: =-'Financial model'!F20 -> 12757.381 | D14: =-'Financial model'!G20 -> 23923.73 | E14: =-'Financial model'!H20 -> 28523.186 | F14: =-'Financial model'!I20 -> 33814.913 | G14: =-'Financial model'!J20 -> 39892.592 | H14: =-'Financial model'!K20 -> 46861.848 | I14: =-'Financial model'!L20 -> 54841.713 | J14: =-'Financial model'!M20 -> 63966.269 | ... L14: =-'Financial model'!O20 -> 86272.243
B15: Adjust for changes in net working capital:
B16: Subtract increase in current assets | C16: =-('Financial model'!F29-'Financial model'!E29) -> 23353.91 | D16: =-('Financial model'!G29-'Financial model'!F29) -> -7061.109 | E16: =-('Financial model'!H29-'Financial model'!G29) -> -7767.2199 | F16: =-('Financial model'!I29-'Financial model'!H29) -> -8543.9419 | G16: =-('Financial model'!J29-'Financial model'!I29) -> -9398.3361 | H16: =-('Financial model'!K29-'Financial model'!J29) -> -10338.17 | I16: =-('Financial model'!L29-'Financial model'!K29) -> -11371.987 | J16: =-('Financial model'!M29-'Financial model'!L29) -> -12509.185 | ... L16: =-('Financial model'!O29-'Financial model'!N29) -> -15136.114
B17: Add back increase in current liabilities | C17: ='Financial model'!F36-'Financial model'!E36 -> -46317.752 | D17: ='Financial model'!G36-'Financial model'!F36 -> 3765.9248 | E17: ='Financial model'!H36-'Financial model'!G36 -> 4142.5173 | F17: ='Financial model'!I36-'Financial model'!H36 -> 4556.769 | G17: ='Financial model'!J36-'Financial model'!I36 -> 5012.4459 | H17: ='Financial model'!K36-'Financial model'!J36 -> 5513.6905 | I17: ='Financial model'!L36-'Financial model'!K36 -> 6065.0595 | J17: ='Financial model'!M36-'Financial model'!L36 -> 6671.5655 | ... L17: ='Financial model'!O36-'Financial model'!N36 -> 8072.5943
B18: Net cash from operating activities | C18: =SUM(C13:C17) -> 76443.123 | D18: =SUM(D13:D17) -> 105017.51 | E18: =SUM(E13:E17) -> 118000.09 | F18: =SUM(F13:F17) -> 132353.26 | G18: =SUM(G13:G17) -> 148216.79 | H18: =SUM(H13:H17) -> 165744.62 | I18: =SUM(I13:I17) -> 185106.22 | J18: =SUM(J13:J17) -> 206488.22 | ... L18: =SUM(L13:L17) -> 256156.18
B20: Cash flow from investing activities
B21: Aquisitions of fixed assets--capital expenditures | C21: =-('Financial model'!F31-'Financial model'!E31) -> -180573.62 | D21: =-('Financial model'!G31-'Financial model'!F31) -> -42753.354 | E21: =-('Financial model'!H31-'Financial model'!G31) -> -49235.773 | F21: =-('Financial model'!I31-'Financial model'!H31) -> -56598.758 | G21: =-('Financial model'!J31-'Financial model'!I31) -> -64954.821 | H21: =-('Financial model'!K31-'Financial model'!J31) -> -74430.3 | I21: =-('Financial model'!L31-'Financial model'!K31) -> -85167.011 | J21: =-('Financial model'!M31-'Financial model'!L31) -> -97324.096 | ... L21: =-('Financial model'!O31-'Financial model'!N31) -> -126635.21
B22: Purchases of investment securities
B23: Proceeds from sales of investment securities
B24: Net cash used in investing activities | C24: =SUM(C21:C23) -> -180573.62 | D24: =SUM(D21:D23) -> -42753.354 | E24: =SUM(E21:E23) -> -49235.773 | F24: =SUM(F21:F23) -> -56598.758 | G24: =SUM(G21:G23) -> -64954.821 | H24: =SUM(H21:H23) -> -74430.3 | I24: =SUM(I21:I23) -> -85167.011 | J24: =SUM(J21:J23) -> -97324.096 | ... L24: =SUM(L21:L23) -> -126635.21
B26: Cash flow from financing activities
B27: Net proceeds from borrowing activities | C27: ='Financial model'!F37-'Financial model'!E37 -> 30113.875 | D27: ='Financial model'!G37-'Financial model'!F37 -> 25316.689 | E27: ='Financial model'!H37-'Financial model'!G37 -> 27930.482 | F27: ='Financial model'!I37-'Financial model'!H37 -> 30757.656 | G27: ='Financial model'!J37-'Financial model'!I37 -> 33813.027 | H27: ='Financial model'!K37-'Financial model'!J37 -> 37112.174 | I27: ='Financial model'!L37-'Financial model'!K37 -> 40671.43 | J27: ='Financial model'!M37-'Financial model'!L37 -> 44507.872 | ... L27: ='Financial model'!O37-'Financial model'!N37 -> 53084.238
B28: Net proceeds from stock issues, repurchases
B29: Dividends paid | C29: ='Financial model'!F24 -> -34659.834 | D29: ='Financial model'!G24 -> -33755.586 | E29: ='Financial model'!H24 -> -37240.643 | F29: ='Financial model'!I24 -> -41010.207 | G29: ='Financial model'!J24 -> -45084.037 | H29: ='Financial model'!K24 -> -49482.899 | I29: ='Financial model'!L24 -> -54228.573 | J29: ='Financial model'!M24 -> -59343.829 | ... L29: ='Financial model'!O24 -> -70778.984
B30: Net cash from financing activities | C30: =SUM(C27:C29) -> -4545.9584 | D30: =SUM(D27:D29) -> -8438.8964 | E30: =SUM(E27:E29) -> -9310.1608 | F30: =SUM(F27:F29) -> -10252.552 | G30: =SUM(G27:G29) -> -11271.009 | H30: =SUM(H27:H29) -> -12370.725 | I30: =SUM(I27:I29) -> -13557.143 | J30: =SUM(J27:J29) -> -14835.957 | ... L30: =SUM(L27:L29) -> -17694.746
B32: Net increase in cash and cash equivalents | C32: =C18+C24+C30 -> -108676.46 | D32: =D18+D24+D30 -> 53825.259 | E32: =E18+E24+E30 -> 59454.158 | F32: =F18+F24+F30 -> 65501.949 | G32: =G18+G24+G30 -> 71990.963 | H32: =H18+H24+H30 -> 78943.592 | I32: =I18+I24+I30 -> 86382.064 | J32: =J18+J24+J30 -> 94328.168 | ... L32: =L18+L24+L30 -> 111826.22
B33: Check: changes in cash and mkt. securities | C33: ='Financial model'!F28-'Financial model'!E28+'Financial model'!E28 -> -108676.46 | D33: ='Financial model'!G28-'Financial model'!F28 -> 53825.259 | E33: ='Financial model'!H28-'Financial model'!G28 -> 59454.158 | F33: ='Financial model'!I28-'Financial model'!H28 -> 65501.949 | G33: ='Financial model'!J28-'Financial model'!I28 -> 71990.963 | H33: ='Financial model'!K28-'Financial model'!J28 -> 78943.592 | I33: ='Financial model'!L28-'Financial model'!K28 -> 86382.064 | J33: ='Financial model'!M28-'Financial model'!L28 -> 94328.168 | K33: ='Financial model'!N28-'Financial model'!M28 -> 102802.93 | L33: ='Financial model'!O28-'Financial model'!N28 -> 111826.22
